VitiroverPIP/__init__.py
VitiroverPIP/control.py
VitiroverPIP/telemetry_pb2.py
vitirover/__init__.py
vitirover/control.py
vitirover/telemetry_pb2.py
vitirover-1.0.dist-info/METADATA
vitirover-1.0.dist-info/WHEEL
vitirover-1.0.dist-info/top_level.txt
vitirover-1.0.dist-info/RECORD
