Metadata-Version: 2.1
Name: vitirover
Version: 1.0
Summary: Commande du robot Vitirover avec le clavier.
Home-page: https://github.com/votreusername/vitirover
Author: Jorand Gallou
Author-email: info@vitirover.com
License: MIT
Keywords: vitirover robot control pygame
Requires-Dist: pygame
Requires-Dist: protobuf
